base66u/__init__.py
base66u/alphabet.py
base66u/checksum.py
base66u/core.py
base66u/exceptions.py
base66u-1.0.0.dist-info/licenses/LICENSE
base66u-1.0.0.dist-info/METADATA
base66u-1.0.0.dist-info/WHEEL
base66u-1.0.0.dist-info/top_level.txt
base66u-1.0.0.dist-info/RECORD
