Metadata-Version: 2.4
Name: base66u
Version: 1.0.0
Summary: Base66U - URL-safe, padding-free encoding with optional checksum
Author-email: MuerteSeguraZ <northkoreanukeslmao@gmail.com>
License: MIT License
Keywords: base66,encoding,url-safe,checksum
Classifier: Programming Language :: Python :: 3
Classifier: License :: OSI Approved :: MIT License
Classifier: Operating System :: OS Independent
Requires-Python: >=3.7
License-File: LICENSE
Dynamic: license-file
